CPU/cpu_32bit.v
`timescale 1ns/1ps

module regfile_32bit (
    input  wire        clk,
    input  wire        rst,
    input  wire        write_en,
    input  wire [4:0]  write_addr,
    input  wire [4:0]  read_addr_1,
    input  wire [4:0]  read_addr_2,
    input  wire [31:0] write_data,
    output wire [31:0] read_data_1,
    output wire [31:0] read_data_2
);

    reg [31:0] regs [0:7];
    integer i;

    assign read_data_1 = (read_addr_1 == 5'b00000) ? 32'h00000000 : regs[read_addr_1[2:0]];
    assign read_data_2 = (read_addr_2 == 5'b00000) ? 32'h00000000 : regs[read_addr_2[2:0]];

    always @(posedge clk or posedge rst) begin
        if (rst) begin
            for (i = 0; i < 8; i = i + 1)
                regs[i] <= 32'h00000000;
        end else if (write_en && write_addr != 5'b00000) begin
            regs[write_addr[2:0]] <= write_data;
        end
    end

endmodule

module alu_32bit (
    input  wire [31:0] val_a,
    input  wire [31:0] val_b,
    input  wire [3:0]  ctrl_op,
    output reg  [31:0] val_out,
    output wire        zero_out
);

    localparam [3:0] ALU_ADD = 4'b0000;
    localparam [3:0] ALU_SUB = 4'b0001;
    localparam [3:0] ALU_AND = 4'b0010;
    localparam [3:0] ALU_OR  = 4'b0011;
    localparam [3:0] ALU_XOR = 4'b0100;
    localparam [3:0] ALU_SLL = 4'b0101;
    localparam [3:0] ALU_SRL = 4'b0110;
    localparam [3:0] ALU_SLT = 4'b0111;

    always @(*) begin
        case (ctrl_op)
            ALU_ADD: val_out = val_a + val_b;
            ALU_SUB: val_out = val_a - val_b;
            ALU_AND: val_out = val_a & val_b;
            ALU_OR: val_out = val_a | val_b;
            ALU_XOR: val_out = val_a ^ val_b;
            ALU_SLL: val_out = val_a << val_b[4:0];
            ALU_SRL: val_out = val_a >> val_b[4:0];
            ALU_SLT: val_out = ($signed(val_a) < $signed(val_b)) ? 32'h00000001 : 32'h00000000;
            default: val_out = 32'h00000000;
        endcase
    end

    assign zero_out = (val_out == 32'h00000000);

endmodule

module ctrl_unit (
    input  wire [4:0] instr_op,
    output reg        do_regwr,
    output reg        do_memrd,
    output reg        do_memwr,
    output reg        alu_use_imm,
    output reg        wb_from_mem,
    output reg        do_branch,
    output reg        do_jump,
    output reg        do_halt,
    output reg [3:0]  alu_func
);

    localparam [4:0] OP_ADD  = 5'b00000;
    localparam [4:0] OP_SUB  = 5'b00001;
    localparam [4:0] OP_AND  = 5'b00010;
    localparam [4:0] OP_OR   = 5'b00011;
    localparam [4:0] OP_XOR  = 5'b00100;
    localparam [4:0] OP_ADDI = 5'b01000;
    localparam [4:0] OP_ANDI = 5'b01001;
    localparam [4:0] OP_ORI  = 5'b01010;
    localparam [4:0] OP_LW   = 5'b01011;
    localparam [4:0] OP_SW   = 5'b01100;
    localparam [4:0] OP_BEQ  = 5'b01101;
    localparam [4:0] OP_JMP  = 5'b01110;
    localparam [4:0] OP_HALT = 5'b11111;

    always @(*) begin
        do_regwr = 1'b0;
        do_memrd = 1'b0;
        do_memwr = 1'b0;
        alu_use_imm = 1'b0;
        wb_from_mem = 1'b0;
        do_branch = 1'b0;
        do_jump = 1'b0;
        do_halt = 1'b0;
        alu_func = 4'b0000;

        case (instr_op)
            OP_ADD: begin
                do_regwr = 1'b1;
                alu_func = 4'b0000;
            end
            OP_SUB: begin
                do_regwr = 1'b1;
                alu_func = 4'b0001;
            end
            OP_AND: begin
                do_regwr = 1'b1;
                alu_func = 4'b0010;
            end
            OP_OR: begin
                do_regwr = 1'b1;
                alu_func = 4'b0011;
            end
            OP_XOR: begin
                do_regwr = 1'b1;
                alu_func = 4'b0100;
            end
            OP_ADDI: begin
                do_regwr = 1'b1;
                alu_use_imm = 1'b1;
                alu_func = 4'b0000;
            end
            OP_ANDI: begin
                do_regwr = 1'b1;
                alu_use_imm = 1'b1;
                alu_func = 4'b0010;
            end
            OP_ORI: begin
                do_regwr = 1'b1;
                alu_use_imm = 1'b1;
                alu_func = 4'b0011;
            end
            OP_LW: begin
                do_regwr = 1'b1;
                do_memrd = 1'b1;
                wb_from_mem = 1'b1;
                alu_use_imm = 1'b1;
                alu_func = 4'b0000;
            end
            OP_SW: begin
                do_memwr = 1'b1;
                alu_use_imm = 1'b1;
                alu_func = 4'b0000;
            end
            OP_BEQ: begin
                do_branch = 1'b1;
                alu_func = 4'b0001;
            end
            OP_JMP: begin
                do_jump = 1'b1;
            end
            OP_HALT: begin
                do_halt = 1'b1;
            end
            default: begin
            end
        endcase
    end

endmodule

module cpu_32bit (
    input  wire        clk,
    input  wire        rst,
    input  wire [31:0] instr,
    input  wire [31:0] mem_data_in,
    output wire [31:0] pc_out,
    output wire [31:0] mem_addr_out,
    output wire [31:0] mem_data_out,
    output wire        mem_we,
    output wire        mem_re,
    output wire        cpu_halted
);

    wire [4:0]  op_code;
    wire [4:0]  dst_reg;
    wire [4:0]  src_reg_1;
    wire [4:0]  src_reg_2;
    wire [16:0] imm_value;
    wire [31:0] imm_ext;

    assign op_code = instr[31:27];
    assign dst_reg = instr[26:22];
    assign src_reg_1 = instr[21:17];
    assign src_reg_2 = instr[16:12];
    assign imm_value = instr[16:0];
    assign imm_ext = {{15{imm_value[16]}}, imm_value};

    wire do_regwr, do_memrd, do_memwr, alu_use_imm, wb_from_mem, do_branch, do_jump, halted_sig;
    wire [3:0] alu_func;

    ctrl_unit CTRL (
        .instr_op(op_code),
        .do_regwr(do_regwr),
        .do_memrd(do_memrd),
        .do_memwr(do_memwr),
        .alu_use_imm(alu_use_imm),
        .wb_from_mem(wb_from_mem),
        .do_branch(do_branch),
        .do_jump(do_jump),
        .do_halt(halted_sig),
        .alu_func(alu_func)
    );

    wire [31:0] src_val_1, src_val_2;
    wire [31:0] wb_data;
    wire [31:0] alu_out;
    wire [31:0] alu_in_2;
    wire        alu_zero;

    assign wb_data = wb_from_mem ? mem_data_in : alu_out;

    regfile_32bit REGS (
        .clk(clk),
        .rst(rst),
        .write_en(do_regwr & ~cpu_halted),
        .write_addr(dst_reg),
        .read_addr_1(src_reg_1),
        .read_addr_2(src_reg_2),
        .write_data(wb_data),
        .read_data_1(src_val_1),
        .read_data_2(src_val_2)
    );

    assign alu_in_2 = alu_use_imm ? imm_ext : src_val_2;

    alu_32bit ALU (
        .val_a(src_val_1),
        .val_b(alu_in_2),
        .ctrl_op(alu_func),
        .val_out(alu_out),
        .zero_out(alu_zero)
    );

    assign mem_addr_out = alu_out;
    assign mem_data_out = src_val_2;
    assign mem_we = do_memwr & ~cpu_halted;
    assign mem_re = do_memrd & ~cpu_halted;

    reg [31:0] pc_reg;
    wire [31:0] pc_next_seq;
    wire [31:0] pc_next_branch;
    wire [31:0] pc_next_jump;
    wire        take_branch;

    assign pc_out = pc_reg;
    assign pc_next_seq = pc_reg + 32'h00000004;
    assign pc_next_branch = pc_reg + (imm_ext << 2);
    assign pc_next_jump = imm_ext;
    assign take_branch = do_branch & alu_zero;

    wire [31:0] pc_next_val;
    assign pc_next_val = do_jump ? pc_next_jump : (take_branch ? pc_next_branch : pc_next_seq);

    always @(posedge clk or posedge rst) begin
        if (rst)
            pc_reg <= 32'h00000000;
        else if (~cpu_halted)
            pc_reg <= pc_next_val;
    end

    reg halted_reg;
    always @(posedge clk or posedge rst) begin
        if (rst)
            halted_reg <= 1'b0;
        else if (halted_sig)
            halted_reg <= 1'b1;
    end

    assign cpu_halted = halted_reg;

endmodule

CPU/tb_cpu_32bit.v
`timescale 1ns/1ps

module tb_cpu_32bit;

    reg         clk;
    reg         rst;
    wire [31:0] pc;
    wire [31:0] mem_addr;
    wire [31:0] mem_data_out;
    wire        mem_we;
    wire        mem_re;
    wire        halted;

    reg [31:0] instr_mem [0:255];
    reg [31:0] data_mem [0:255];
    reg [31:0] instr;
    reg [31:0] mem_data_in;

    integer cycle;
    integer max_cycles;
    integer i;

    function [31:0] encode_rtype;
        input [4:0] op, dst, src1, src2;
        begin
            encode_rtype = {op, dst, src1, src2, 12'b0};
        end
    endfunction

    function [31:0] encode_itype;
        input [4:0] op, dst, src1;
        input [16:0] imm;
        begin
            encode_itype = {op, dst, src1, imm};
        end
    endfunction

    cpu_32bit DUT (
        .clk(clk),
        .rst(rst),
        .instr(instr),
        .mem_data_in(mem_data_in),
        .pc_out(pc),
        .mem_addr_out(mem_addr),
        .mem_data_out(mem_data_out),
        .mem_we(mem_we),
        .mem_re(mem_re),
        .cpu_halted(halted)
    );

    initial begin
        clk = 1'b0;
        forever #5 clk = ~clk;
    end

    always @(*) begin
        instr = instr_mem[pc[9:2]];
    end

    always @(posedge clk) begin
        if (mem_we) begin
            data_mem[mem_addr[9:2]] <= mem_data_out;
            $display("[%0t] WRITE: Addr=0x%h Data=0x%h", $time, mem_addr, mem_data_out);
        end
    end

    always @(*) begin
        if (mem_re)
            mem_data_in = data_mem[mem_addr[9:2]];
        else
            mem_data_in = 32'h00000000;
    end

    initial begin
        $display("====================================================");
        $display("           32-bit CPU Test");
        $display("====================================================\n");

        // Initialize all instruction memory to HALT to avoid x's
        for (i = 0; i < 256; i = i + 1)
            instr_mem[i] = {5'b11111, 27'b0};

        instr_mem[0] = encode_itype(5'b01000, 5'd1, 5'd0, 17'd10);
        instr_mem[1] = encode_itype(5'b01000, 5'd2, 5'd0, 17'd20);
        instr_mem[2] = encode_rtype(5'b00000, 5'd3, 5'd1, 5'd2);
        instr_mem[3] = encode_rtype(5'b00001, 5'd4, 5'd2, 5'd1);
        instr_mem[4] = encode_rtype(5'b00010, 5'd5, 5'd1, 5'd2);
        instr_mem[5] = encode_rtype(5'b00011, 5'd6, 5'd1, 5'd2);
        instr_mem[6] = encode_rtype(5'b00100, 5'd7, 5'd1, 5'd2);
        instr_mem[7] = encode_itype(5'b01100, 5'd0, 5'd0, 17'd0);
        instr_mem[8] = encode_itype(5'b01100, 5'd0, 5'd0, 17'd4);
        instr_mem[9] = encode_itype(5'b01011, 5'd1, 5'd0, 17'd0);
        instr_mem[10] = {5'b11111, 27'b0};

        rst = 1'b1;
        cycle = 0;
        max_cycles = 50;
        #20;
        rst = 1'b0;

        $display("Starting execution...\n");
        $display("Cycle  PC       Instr       Halted  WE Dst Data");
        $display("------ -------- ----------- ------  -- --- --------");

        while (!halted && cycle < max_cycles) begin
            @(posedge clk);
            $display("%5d  0x%06h  0x%08h    %b  WE=%b Dst=R%0d Data=0x%08h", 
                     cycle, pc, instr, halted, 
                     DUT.do_regwr, DUT.dst_reg, DUT.wb_data);
            cycle = cycle + 1;
        end

        $display("\n====================================================");
        $display("Register File State:");
        $display("  R0 = 0x%08h (always 0)", DUT.REGS.regs[0]);
        $display("  R1 = 0x%08h (expected: 0x0000000A = 10)", DUT.REGS.regs[1]);
        $display("  R2 = 0x%08h (expected: 0x00000014 = 20)", DUT.REGS.regs[2]);
        $display("  R3 = 0x%08h (expected: 0x0000001E = 30)", DUT.REGS.regs[3]);
        $display("  R4 = 0x%08h (expected: 0x0000000A = 10)", DUT.REGS.regs[4]);
        $display("  R5 = 0x%08h", DUT.REGS.regs[5]);
        $display("  R6 = 0x%08h", DUT.REGS.regs[6]);
        $display("  R7 = 0x%08h", DUT.REGS.regs[7]);

        $display("\nMemory State:");
        $display("  Mem[0] = 0x%08h", data_mem[0]);
        $display("  Mem[1] = 0x%08h", data_mem[1]);

        if (DUT.REGS.regs[3] == 32'h0000001E && DUT.REGS.regs[4] == 32'h0000000A) begin
            $display("\nResult: PASSED");
        end else begin
            $display("\nResult: FAILED");
        end

        $display("Total Cycles: %0d", cycle);
        $display("====================================================\n");

        $finish;
    end

    initial begin
        $dumpfile("cpu_32bit.vcd");
        $dumpvars(0, tb_cpu_32bit);
    end

endmodule

CPU/cpu_32bit.vcd
$date
	Fri Jan 30 23:40:19 2026
$end
$version
	Icarus Verilog
$end
$timescale
	1ps
$end
$scope module tb_cpu_32bit $end
$var wire 32 ! pc [31:0] $end
$var wire 1 " mem_we $end
$var wire 1 # mem_re $end
$var wire 32 $ mem_data_out [31:0] $end
$var wire 32 % mem_addr [31:0] $end
$var wire 1 & halted $end
$var reg 1 ' clk $end
$var reg 32 ( instr [31:0] $end
$var reg 32 ) mem_data_in [31:0] $end
$var reg 1 * rst $end
$var integer 32 + cycle [31:0] $end
$var integer 32 , i [31:0] $end
$var integer 32 - max_cycles [31:0] $end
$scope function encode_itype $end
$var reg 5 . dst [4:0] $end
$var reg 17 / imm [16:0] $end
$var reg 5 0 op [4:0] $end
$var reg 5 1 src1 [4:0] $end
$upscope $end
$scope function encode_rtype $end
$var reg 5 2 dst [4:0] $end
$var reg 5 3 op [4:0] $end
$var reg 5 4 src1 [4:0] $end
$var reg 5 5 src2 [4:0] $end
$upscope $end
$scope module DUT $end
$var wire 1 ' clk $end
$var wire 32 6 instr [31:0] $end
$var wire 32 7 mem_addr_out [31:0] $end
$var wire 32 8 mem_data_in [31:0] $end
$var wire 32 9 mem_data_out [31:0] $end
$var wire 1 # mem_re $end
$var wire 1 " mem_we $end
$var wire 32 : pc_next_jump [31:0] $end
$var wire 32 ; pc_out [31:0] $end
$var wire 1 * rst $end
$var wire 1 < take_branch $end
$var wire 1 = wb_from_mem $end
$var wire 32 > wb_data [31:0] $end
$var wire 32 ? src_val_2 [31:0] $end
$var wire 32 @ src_val_1 [31:0] $end
$var wire 5 A src_reg_2 [4:0] $end
$var wire 5 B src_reg_1 [4:0] $end
$var wire 32 C pc_next_val [31:0] $end
$var wire 32 D pc_next_seq [31:0] $end
$var wire 32 E pc_next_branch [31:0] $end
$var wire 5 F op_code [4:0] $end
$var wire 17 G imm_value [16:0] $end
$var wire 32 H imm_ext [31:0] $end
$var wire 1 I halted_sig $end
$var wire 5 J dst_reg [4:0] $end
$var wire 1 K do_regwr $end
$var wire 1 L do_memwr $end
$var wire 1 M do_memrd $end
$var wire 1 N do_jump $end
$var wire 1 O do_branch $end
$var wire 1 & cpu_halted $end
$var wire 1 P alu_zero $end
$var wire 1 Q alu_use_imm $end
$var wire 32 R alu_out [31:0] $end
$var wire 32 S alu_in_2 [31:0] $end
$var wire 4 T alu_func [3:0] $end
$var reg 1 & halted_reg $end
$var reg 32 U pc_reg [31:0] $end
$scope module ALU $end
$var wire 32 V val_b [31:0] $end
$var wire 1 P zero_out $end
$var wire 32 W val_a [31:0] $end
$var wire 4 X ctrl_op [3:0] $end
$var parameter 4 Y ALU_ADD $end
$var parameter 4 Z ALU_AND $end
$var parameter 4 [ ALU_OR $end
$var parameter 4 \ ALU_SLL $end
$var parameter 4 ] ALU_SLT $end
$var parameter 4 ^ ALU_SRL $end
$var parameter 4 _ ALU_SUB $end
$var parameter 4 ` ALU_XOR $end
$var reg 32 a val_out [31:0] $end
$upscope $end
$scope module CTRL $end
$var wire 5 b instr_op [4:0] $end
$var parameter 5 c OP_ADD $end
$var parameter 5 d OP_ADDI $end
$var parameter 5 e OP_AND $end
$var parameter 5 f OP_ANDI $end
$var parameter 5 g OP_BEQ $end
$var parameter 5 h OP_HALT $end
$var parameter 5 i OP_JMP $end
$var parameter 5 j OP_LW $end
$var parameter 5 k OP_OR $end
$var parameter 5 l OP_ORI $end
$var parameter 5 m OP_SUB $end
$var parameter 5 n OP_SW $end
$var parameter 5 o OP_XOR $end
$var reg 4 p alu_func [3:0] $end
$var reg 1 Q alu_use_imm $end
$var reg 1 O do_branch $end
$var reg 1 I do_halt $end
$var reg 1 N do_jump $end
$var reg 1 M do_memrd $end
$var reg 1 L do_memwr $end
$var reg 1 K do_regwr $end
$var reg 1 = wb_from_mem $end
$upscope $end
$scope module REGS $end
$var wire 1 ' clk $end
$var wire 5 q read_addr_1 [4:0] $end
$var wire 5 r read_addr_2 [4:0] $end
$var wire 1 * rst $end
$var wire 5 s write_addr [4:0] $end
$var wire 32 t write_data [31:0] $end
$var wire 1 u write_en $end
$var wire 32 v read_data_2 [31:0] $end
$var wire 32 w read_data_1 [31:0] $end
$var integer 32 x i [31:0] $end
$upscope $end
$upscope $end
$upscope $end
$enddefinitions $end
$comment Show the parameter values. $end
$dumpall
b100 o
b1100 n
b1 m
b1010 l
b11 k
b1011 j
b1110 i
b11111 h
b1101 g
b1001 f
b10 e
b1000 d
b0 c
b100 `
b1 _
b110 ^
b111 ]
b101 \
b11 [
b10 Z
b0 Y
$end
#0
$dumpvars
b1000 x
b0 w
b0 v
1u
b1010 t
b1 s
b0 r
b0 q
b0 p
b1000 b
b1010 a
b0 X
b0 W
b1010 V
b0 U
b0 T
b1010 S
b1010 R
1Q
0P
0O
0N
0M
0L
1K
b1 J
0I
b1010 H
b1010 G
b1000 F
b101000 E
b100 D
b100 C
b0 B
b0 A
b0 @
b0 ?
b1010 >
0=
0<
b0 ;
b1010 :
b0 9
b0 8
b1010 7
b1000000010000000000000000001010 6
b10 5
b1 4
b100 3
b111 2
b0 1
b1011 0
b0 /
b1 .
b110010 -
b100000000 ,
b0 +
1*
b0 )
b1000000010000000000000000001010 (
0'
0&
b1010 %
b0 $
0#
0"
b0 !
$end
#5000
b1000 x
1'
#10000
0'
#15000
b1000 x
1'
#20000
0'
0*
#25000
b10100 >
b10100 t
b10100 %
b10100 7
b10100 R
b10100 a
b10100 S
b10100 V
b1000 C
b10 J
b10 s
b10100 :
b10100 H
b10100 G
b1000000100000000000000000010100 (
b1000000100000000000000000010100 6
b1000 D
b1010100 E
b100 !
b100 ;
b100 U
b1 +
1'
#30000
0'
#35000
b11110 >
b11110 t
b11110 %
b11110 7
b11110 R
b11110 a
0Q
1K
b1010 @
b1010 W
b1010 w
b10100 $
b10100 9
b10100 ?
b10100 v
b10100 S
b10100 V
b1100 C
b0 F
b0 b
b11 J
b11 s
b1 B
b1 q
b10 A
b10 r
b10000000000000 :
b10000000000000 H
b10000000000000 G
b110000100010000000000000 (
b110000100010000000000000 6
b1100 D
b1000000000001000 E
b1000 !
b1000 ;
b1000 U
b10 +
1'
#40000
0'
#45000
b1010 >
b1010 t
b1010 S
b1010 V
0P
b1010 %
b1010 7
b1010 R
b1010 a
b10100 @
b10100 W
b10100 w
b1010 $
b1010 9
b1010 ?
b1010 v
b1 T
b1 X
b1 p
1K
b10000 C
b1 F
b1 b
b100 J
b100 s
b10 B
b10 q
b1 A
b1 r
b1000000000000 :
b1000000000000 H
b1000000000000 G
b1001000001000001000000000000 (
b1001000001000001000000000000 6
b10000 D
b100000000001100 E
b1100 !
b1100 ;
b1100 U
b11 +
1'
#50000
0'
#55000
b0 >
b0 t
1P
b0 %
b0 7
b0 R
b0 a
b10100 S
b10100 V
b1010 @
b1010 W
b1010 w
b10100 $
b10100 9
b10100 ?
b10100 v
b10 T
b10 X
b10 p
1K
b10100 C
b10 F
b10 b
b101 J
b101 s
b1 B
b1 q
b10 A
b10 r
b10000000000000 :
b10000000000000 H
b10000000000000 G
b10001010000100010000000000000 (
b10001010000100010000000000000 6
b10100 D
b1000000000010000 E
b10000 !
b10000 ;
b10000 U
b100 +
1'
#60000
0'
#65000
b11110 >
b11110 t
0P
b11110 %
b11110 7
b11110 R
b11110 a
b11 T
b11 X
b11 p
1K
b11000 C
b11 F
b11 b
b110 J
b110 s
b11001100000100010000000000000 (
b11001100000100010000000000000 6
b11000 D
b1000000000010100 E
b10100 !
b10100 ;
b10100 U
b101 +
1'
#70000
0'
#75000
b100 T
b100 X
b100 p
1K
b11100 C
b100 F
b100 b
b111 J
b111 s
b100001110000100010000000000000 (
b100001110000100010000000000000 6
b11100 D
b1000000000011000 E
b11000 !
b11000 ;
b11000 U
b110 +
1'
#80000
0'
#85000
b0 >
b0 t
1"
0u
1P
b0 %
b0 7
b0 R
b0 a
b0 S
b0 V
1Q
1L
b0 T
b0 X
b0 p
0K
b0 @
b0 W
b0 w
b0 $
b0 9
b0 ?
b0 v
b100000 C
b1100 F
b1100 b
b0 J
b0 s
b0 B
b0 q
b0 A
b0 r
b0 :
b0 H
b0 G
b1100000000000000000000000000000 (
b1100000000000000000000000000000 6
b100000 D
b11100 E
b11100 !
b11100 ;
b11100 U
b111 +
1'
#90000
0'
#95000
b100 >
b100 t
0P
b100 %
b100 7
b100 R
b100 a
b100 S
b100 V
b100100 C
b100 :
b100 H
b100 G
b1100000000000000000000000000100 (
b1100000000000000000000000000100 6
b100100 D
b110000 E
b100000 !
b100000 ;
b100000 U
b1000 +
1'
#100000
0'
#105000
b0 >
b0 t
1#
1u
0"
1P
b0 %
b0 7
b0 R
b0 a
1=
1M
1K
1Q
0L
b0 S
b0 V
b101000 C
b1011 F
b1011 b
b1 J
b1 s
b0 :
b0 H
b0 G
b1011000010000000000000000000000 (
b1011000010000000000000000000000 6
b101000 D
b100100 E
b100100 !
b100100 ;
b100100 U
b1001 +
1'
#110000
0'
#115000
0#
0u
1I
0=
0Q
0M
0K
b101100 C
b11111 F
b11111 b
b0 J
b0 s
b11111000000000000000000000000000 (
b11111000000000000000000000000000 6
b101100 D
b101000 E
b101000 !
b101000 ;
b101000 U
b1010 +
1'
#120000
0'
#125000
b110000 C
1&
b110000 D
b101100 E
b101100 !
b101100 ;
b101100 U
b1011 +
1'
#130000
0'
#135000
b1100 +
1'
