ALU/alu_16bit.v
`timescale 1ns/1ps

module alu_16bit #(
    parameter WIDTH = 16
) (
    input  wire [WIDTH-1:0] input_a,
    input  wire [WIDTH-1:0] input_b,
    input  wire [3:0]       operation,
    output reg  [WIDTH-1:0] output_result,
    output wire             zero_flag,
    output wire             carry_flag,
    output wire             overflow_flag,
    output wire             negative_flag,
    output wire             parity_flag
);

    localparam [3:0] OP_ADD   = 4'b0000;
    localparam [3:0] OP_SUB   = 4'b0001;
    localparam [3:0] OP_INC   = 4'b0010;
    localparam [3:0] OP_DEC   = 4'b0011;
    localparam [3:0] OP_AND   = 4'b0100;
    localparam [3:0] OP_OR    = 4'b0101;
    localparam [3:0] OP_XOR   = 4'b0110;
    localparam [3:0] OP_NOT   = 4'b0111;
    localparam [3:0] OP_SLL   = 4'b1000;
    localparam [3:0] OP_SRL   = 4'b1001;
    localparam [3:0] OP_SRA   = 4'b1010;
    localparam [3:0] OP_EQ    = 4'b1011;
    localparam [3:0] OP_SLT   = 4'b1100;
    localparam [3:0] OP_SLTU  = 4'b1101;
    localparam [3:0] OP_NAND  = 4'b1110;
    localparam [3:0] OP_NOR   = 4'b1111;

    reg [WIDTH:0] temp_result;
    wire [WIDTH-1:0] a_unsigned;
    wire [WIDTH-1:0] b_unsigned;

    assign a_unsigned = input_a;
    assign b_unsigned = input_b;

    always @(*) begin
        output_result = {WIDTH{1'b0}};
        temp_result = {WIDTH+1{1'b0}};

        case (operation)
            OP_ADD: begin
                temp_result = {1'b0, input_a} + {1'b0, input_b};
                output_result = temp_result[WIDTH-1:0];
            end
            
            OP_SUB: begin
                temp_result = {1'b0, input_a} + {1'b0, ~input_b} + 1;
                output_result = temp_result[WIDTH-1:0];
            end
            
            OP_INC: begin
                temp_result = {1'b0, input_a} + 1;
                output_result = temp_result[WIDTH-1:0];
            end
            
            OP_DEC: begin
                temp_result = {1'b0, input_a} - 1;
                output_result = temp_result[WIDTH-1:0];
            end

            OP_AND: 
                output_result = input_a & input_b;
            
            OP_OR: 
                output_result = input_a | input_b;
            
            OP_XOR: 
                output_result = input_a ^ input_b;
            
            OP_NOT: 
                output_result = ~input_a;

            OP_SLL: 
                output_result = input_a << input_b[3:0];
            
            OP_SRL: 
                output_result = input_a >> input_b[3:0];
            
            OP_SRA: 
                output_result = $signed(input_a) >>> input_b[3:0];

            OP_EQ: 
                output_result = (input_a == input_b) ? 1 : 0;
            
            OP_SLT: 
                output_result = ($signed(input_a) < $signed(input_b)) ? 1 : 0;
            
            OP_SLTU: 
                output_result = (input_a < input_b) ? 1 : 0;

            OP_NAND: 
                output_result = ~(input_a & input_b);
            
            OP_NOR: 
                output_result = ~(input_a | input_b);

            default: 
                output_result = {WIDTH{1'b0}};
        endcase
    end

    assign zero_flag = (output_result == {WIDTH{1'b0}});
    assign negative_flag = output_result[WIDTH-1];
    assign parity_flag = ^output_result;

    wire sign_a = input_a[WIDTH-1];
    wire sign_b = input_b[WIDTH-1];
    wire sign_result = output_result[WIDTH-1];

    assign carry_flag = (operation == OP_SUB) ? ~temp_result[WIDTH] : temp_result[WIDTH];
    assign overflow_flag = (operation == OP_ADD) ? ((~sign_a & ~sign_b & sign_result) | (sign_a & sign_b & ~sign_result)) :
                          (operation == OP_SUB) ? ((~sign_a & sign_b & sign_result) | (sign_a & ~sign_b & ~sign_result)) :
                          (operation == OP_INC) ? (~sign_a & sign_result) :
                          (operation == OP_DEC) ? (sign_a & ~sign_result) : 1'b0;

endmodule

ALU/tb_alu_16bit.v
`timescale 1ns/1ps

module tb_alu_16bit;

    reg  [15:0] a;
    reg  [15:0] b;
    reg  [3:0]  op;
    wire [15:0] result;
    wire        zero;
    wire        carry;
    wire        overflow;
    wire        negative;
    wire        parity;

    integer total;
    integer pass;
    integer fail;

    localparam [3:0] OP_ADD   = 4'b0000;
    localparam [3:0] OP_SUB   = 4'b0001;
    localparam [3:0] OP_INC   = 4'b0010;
    localparam [3:0] OP_DEC   = 4'b0011;
    localparam [3:0] OP_AND   = 4'b0100;
    localparam [3:0] OP_OR    = 4'b0101;
    localparam [3:0] OP_XOR   = 4'b0110;
    localparam [3:0] OP_NOT   = 4'b0111;
    localparam [3:0] OP_SLL   = 4'b1000;
    localparam [3:0] OP_SRL   = 4'b1001;
    localparam [3:0] OP_SRA   = 4'b1010;
    localparam [3:0] OP_EQ    = 4'b1011;
    localparam [3:0] OP_SLT   = 4'b1100;
    localparam [3:0] OP_SLTU  = 4'b1101;
    localparam [3:0] OP_NAND  = 4'b1110;
    localparam [3:0] OP_NOR   = 4'b1111;

    alu_16bit DUT (
        .input_a(a),
        .input_b(b),
        .operation(op),
        .output_result(result),
        .zero_flag(zero),
        .carry_flag(carry),
        .overflow_flag(overflow),
        .negative_flag(negative),
        .parity_flag(parity)
    );

    task verify;
        input [15:0] exp_res;
        input        exp_z;
        input        exp_c;
        input        exp_o;
        input        exp_n;
        input        exp_p;
        input [80:0] msg;
        begin
            total = total + 1;
            #1;
            
            if (result === exp_res && zero === exp_z && carry === exp_c && 
                overflow === exp_o && negative === exp_n && parity === exp_p) begin
                $display("[OK] %0d. %s", total, msg);
                pass = pass + 1;
            end else begin
                $display("[XX] %0d. %s", total, msg);
                $display("     In: A=0x%h, B=0x%h, OP=%b", a, b, op);
                $display("     Exp: R=0x%h Z=%b C=%b O=%b N=%b P=%b", exp_res, exp_z, exp_c, exp_o, exp_n, exp_p);
                $display("     Got: R=0x%h Z=%b C=%b O=%b N=%b P=%b", result, zero, carry, overflow, negative, parity);
                fail = fail + 1;
            end
        end
    endtask

    initial begin
        total = 0;
        pass = 0;
        fail = 0;

        $display("================================");
        $display("    16-bit ALU Test Suite");
        $display("================================\n");

        $display("ARITHMETIC OPERATIONS\n");

        a = 16'h0007; b = 16'h0005; op = OP_ADD; #10;
        verify(16'h000C, 1'b0, 1'b0, 1'b0, 1'b0, 1'b0, "7 + 5");

        a = 16'h0000; b = 16'h0000; op = OP_ADD; #10;
        verify(16'h0000, 1'b1, 1'b0, 1'b0, 1'b0, 1'b0, "0 + 0 zero flag");

        a = 16'hFFFF; b = 16'h0001; op = OP_ADD; #10;
        verify(16'h0000, 1'b1, 1'b1, 1'b0, 1'b0, 1'b0, "Max + 1 overflow");

        a = 16'h7FFF; b = 16'h0001; op = OP_ADD; #10;
        verify(16'h8000, 1'b0, 1'b0, 1'b1, 1'b1, 1'b0, "Pos overflow");

        a = 16'h8000; b = 16'h8000; op = OP_ADD; #10;
        verify(16'h0000, 1'b1, 1'b1, 1'b1, 1'b0, 1'b0, "Neg overflow");

        a = 16'h0009; b = 16'h0003; op = OP_SUB; #10;
        verify(16'h0006, 1'b0, 1'b0, 1'b0, 1'b0, 1'b1, "9 - 3");

        a = 16'h0003; b = 16'h0009; op = OP_SUB; #10;
        verify(16'hFFFC, 1'b0, 1'b1, 1'b0, 1'b1, 1'b1, "3 - 9 negative");

        a = 16'h0000; b = 16'h0000; op = OP_SUB; #10;
        verify(16'h0000, 1'b1, 1'b0, 1'b0, 1'b0, 1'b0, "0 - 0");

        a = 16'h0005; b = 16'h0000; op = OP_INC; #10;
        verify(16'h0006, 1'b0, 1'b0, 1'b0, 1'b0, 1'b1, "5 increment");

        a = 16'hFFFF; b = 16'h0000; op = OP_INC; #10;
        verify(16'h0000, 1'b1, 1'b1, 1'b0, 1'b0, 1'b0, "Max increment");

        a = 16'h0005; b = 16'h0000; op = OP_DEC; #10;
        verify(16'h0004, 1'b0, 1'b0, 1'b0, 1'b0, 1'b0, "5 decrement");

        a = 16'h0000; b = 16'h0000; op = OP_DEC; #10;
        verify(16'hFFFF, 1'b0, 1'b1, 1'b0, 1'b1, 1'b0, "0 decrement");

        $display("\nLOGICAL OPERATIONS\n");

        a = 16'h00FF; b = 16'hFF00; op = OP_AND; #10;
        verify(16'h0000, 1'b1, 1'b0, 1'b0, 1'b0, 1'b0, "AND zero");

        a = 16'h1234; b = 16'h5678; op = OP_AND; #10;
        verify(16'h1230, 1'b0, 1'b0, 1'b0, 1'b0, 1'b0, "AND patterns");

        a = 16'h00FF; b = 16'hFF00; op = OP_OR; #10;
        verify(16'hFFFF, 1'b0, 1'b0, 1'b0, 1'b1, 1'b0, "OR all ones");

        a = 16'h1234; b = 16'h5678; op = OP_XOR; #10;
        verify(16'h444C, 1'b0, 1'b0, 1'b0, 1'b0, 1'b1, "XOR patterns");

        a = 16'h00FF; b = 16'h0000; op = OP_NOT; #10;
        verify(16'hFF00, 1'b0, 1'b0, 1'b0, 1'b1, 1'b0, "NOT");

        a = 16'h0000; b = 16'h0000; op = OP_NAND; #10;
        verify(16'hFFFF, 1'b0, 1'b0, 1'b0, 1'b1, 1'b0, "NAND zeros");

        a = 16'hFFFF; b = 16'hFFFF; op = OP_NOR; #10;
        verify(16'h0000, 1'b1, 1'b0, 1'b0, 1'b0, 1'b0, "NOR ones");

        $display("\nSHIFT OPERATIONS\n");

        a = 16'h0001; b = 16'h0004; op = OP_SLL; #10;
        verify(16'h0010, 1'b0, 1'b0, 1'b0, 1'b0, 1'b0, "SLL: 1 << 4");

        a = 16'h8000; b = 16'h0004; op = OP_SRL; #10;
        verify(16'h0800, 1'b0, 1'b0, 1'b0, 1'b0, 1'b0, "SRL: 0x8000 >> 4");

        a = 16'h8000; b = 16'h0004; op = OP_SRA; #10;
        verify(16'hF800, 1'b0, 1'b0, 1'b0, 1'b1, 1'b0, "SRA: sign extend");

        a = 16'hFFFF; b = 16'h0002; op = OP_SRA; #10;
        verify(16'hFFFF, 1'b0, 1'b0, 1'b0, 1'b1, 1'b0, "SRA: all ones");

        $display("\nCOMPARISON OPERATIONS\n");

        a = 16'h0005; b = 16'h0005; op = OP_EQ; #10;
        verify(16'h0001, 1'b0, 1'b0, 1'b0, 1'b0, 1'b0, "Equal true");

        a = 16'h0005; b = 16'h0003; op = OP_EQ; #10;
        verify(16'h0000, 1'b1, 1'b0, 1'b0, 1'b0, 1'b0, "Equal false");

        a = 16'h0003; b = 16'h0005; op = OP_SLT; #10;
        verify(16'h0001, 1'b0, 1'b0, 1'b0, 1'b0, 1'b0, "SLT: 3 < 5");

        a = 16'hFFFE; b = 16'h0001; op = OP_SLT; #10;
        verify(16'h0001, 1'b0, 1'b0, 1'b0, 1'b0, 1'b0, "SLT: -2 < 1 signed");

        a = 16'hFFFE; b = 16'h0001; op = OP_SLTU; #10;
        verify(16'h0000, 1'b1, 1'b0, 1'b0, 1'b0, 1'b0, "SLTU: 65534 < 1");

        $display("\nEDGE CASES\n");

        a = 16'h0001; b = 16'h000F; op = OP_SLL; #10;
        verify(16'h8000, 1'b0, 1'b0, 1'b0, 1'b1, 1'b0, "Max shift left");

        a = 16'hAAAA; b = 16'h5555; op = OP_XOR; #10;
        verify(16'hFFFF, 1'b0, 1'b0, 1'b0, 1'b1, 1'b0, "Alternating pattern");

        a = 16'h0001; b = 16'h0000; op = OP_AND; #10;
        verify(16'h0000, 1'b1, 1'b0, 1'b0, 1'b0, 1'b0, "AND clears all");

        #10;
        $display("\n================================");
        $display("Total: %0d | Pass: %0d | Fail: %0d", total, pass, fail);
        if (fail == 0)
            $display("Result: ALL TESTS PASSED");
        else
            $display("Result: FAILED");
        $display("================================\n");

        $finish;
    end

    initial begin
        $dumpfile("alu_16bit.vcd");
        $dumpvars(0, tb_alu_16bit);
    end

endmodule

ALU/alu_16bit.vcd
$date
	Fri Jan 30 23:50:24 2026
$end
$version
	Icarus Verilog
$end
$timescale
	1ps
$end
$scope module tb_alu_16bit $end
$var wire 1 ! zero $end
$var wire 16 " result [15:0] $end
$var wire 1 # parity $end
$var wire 1 $ overflow $end
$var wire 1 % negative $end
$var wire 1 & carry $end
$var parameter 4 ' OP_ADD $end
$var parameter 4 ( OP_AND $end
$var parameter 4 ) OP_DEC $end
$var parameter 4 * OP_EQ $end
$var parameter 4 + OP_INC $end
$var parameter 4 , OP_NAND $end
$var parameter 4 - OP_NOR $end
$var parameter 4 . OP_NOT $end
$var parameter 4 / OP_OR $end
$var parameter 4 0 OP_SLL $end
$var parameter 4 1 OP_SLT $end
$var parameter 4 2 OP_SLTU $end
$var parameter 4 3 OP_SRA $end
$var parameter 4 4 OP_SRL $end
$var parameter 4 5 OP_SUB $end
$var parameter 4 6 OP_XOR $end
$var reg 16 7 a [15:0] $end
$var reg 16 8 b [15:0] $end
$var reg 4 9 op [3:0] $end
$var integer 32 : fail [31:0] $end
$var integer 32 ; pass [31:0] $end
$var integer 32 < total [31:0] $end
$scope module DUT $end
$var wire 16 = a_unsigned [15:0] $end
$var wire 16 > b_unsigned [15:0] $end
$var wire 16 ? input_a [15:0] $end
$var wire 16 @ input_b [15:0] $end
$var wire 4 A operation [3:0] $end
$var wire 1 ! zero_flag $end
$var wire 1 B sign_result $end
$var wire 1 C sign_b $end
$var wire 1 D sign_a $end
$var wire 1 # parity_flag $end
$var wire 1 $ overflow_flag $end
$var wire 1 % negative_flag $end
$var wire 1 & carry_flag $end
$var parameter 4 E OP_ADD $end
$var parameter 4 F OP_AND $end
$var parameter 4 G OP_DEC $end
$var parameter 4 H OP_EQ $end
$var parameter 4 I OP_INC $end
$var parameter 4 J OP_NAND $end
$var parameter 4 K OP_NOR $end
$var parameter 4 L OP_NOT $end
$var parameter 4 M OP_OR $end
$var parameter 4 N OP_SLL $end
$var parameter 4 O OP_SLT $end
$var parameter 4 P OP_SLTU $end
$var parameter 4 Q OP_SRA $end
$var parameter 4 R OP_SRL $end
$var parameter 4 S OP_SUB $end
$var parameter 4 T OP_XOR $end
$var parameter 32 U WIDTH $end
$var reg 16 V output_result [15:0] $end
$var reg 17 W temp_result [16:0] $end
$upscope $end
$scope task verify $end
$var reg 1 X exp_c $end
$var reg 1 Y exp_n $end
$var reg 1 Z exp_o $end
$var reg 1 [ exp_p $end
$var reg 16 \ exp_res [15:0] $end
$var reg 1 ] exp_z $end
$var reg 81 ^ msg [80:0] $end
$upscope $end
$upscope $end
$enddefinitions $end
$comment Show the parameter values. $end
$dumpall
b10000 U
b110 T
b1 S
b1001 R
b1010 Q
b1101 P
b1100 O
b1000 N
b101 M
b111 L
b1111 K
b1110 J
b10 I
b1011 H
b11 G
b100 F
b0 E
b110 6
b1 5
b1001 4
b1010 3
b1101 2
b1100 1
b1000 0
b101 /
b111 .
b1111 -
b1110 ,
b10 +
b1011 *
b11 )
b100 (
b0 '
$end
#0
$dumpvars
bx ^
x]
bx \
x[
xZ
xY
xX
b1100 W
b1100 V
0D
0C
0B
b0 A
b101 @
b111 ?
b101 >
b111 =
b0 <
b0 ;
b0 :
b0 9
b101 8
b111 7
0&
0%
0$
0#
b1100 "
0!
$end
#10000
b1 <
b11011100100000001010110010000000110101 ^
0[
0Y
0Z
0X
0]
b1100 \
#11000
b0 W
1!
b0 "
b0 V
b0 >
b0 8
b0 @
b0 =
b0 7
b0 ?
b1 ;
#21000
b10 <
b100000011110100110010101110010011011110010000001100110011011000110000101100111 ^
1]
b0 \
#22000
1&
b10000000000000000 W
1D
b1 >
b1 8
b1 @
b1111111111111111 =
b1111111111111111 7
b1111111111111111 ?
b10 ;
#32000
b11 <
b110001001000000110111101110110011001010111001001100110011011000110111101110111 ^
1X
#33000
1$
0&
1%
1B
0!
1#
b1000000000000000 "
b1000000000000000 V
b1000000000000000 W
0D
b111111111111111 =
b111111111111111 7
b111111111111111 ?
b11 ;
#43000
b100 <
b101110011001000000110111101110110011001010111001001100110011011000110111101110111 ^
1Y
1Z
0X
0]
b1000000000000000 \
#44000
1$
1&
0%
0B
1C
b10000000000000000 W
1!
0#
b0 "
b0 V
1D
b1000000000000000 >
b1000000000000000 8
b1000000000000000 @
b1000000000000000 =
b1000000000000000 7
b1000000000000000 ?
b1 :
#54000
b101 <
b101100111001000000110111101110110011001010111001001100110011011000110111101110111 ^
0Y
1X
1]
b0 \
#55000
0&
0$
0C
0!
b110 "
b110 V
b10000000000000110 W
0D
b1 9
b1 A
b11 >
b11 8
b11 @
b1001 =
b1001 7
b1001 ?
b100 ;
#65000
b110 <
b11100100100000001011010010000000110011 ^
1[
0Z
0X
0]
b110 \
#66000
1&
1%
1B
b1111111111111010 W
0!
b1111111111111010 "
b1111111111111010 V
b1001 >
b1001 8
b1001 @
b11 =
b11 7
b11 ?
b10 :
#76000
b111 <
b111001001000000110111001100101011001110110000101110100011010010111011001100101 ^
1Y
1X
b1111111111111100 \
#77000
0&
0%
0B
b10000000000000000 W
1!
b0 "
b0 V
b0 >
b0 8
b0 @
b0 =
b0 7
b0 ?
b11 :
#87000
b1000 <
b11000000100000001011010010000000110000 ^
0[
0Y
0X
1]
b0 \
#88000
0&
0!
b110 "
b110 V
b110 W
b10 9
b10 A
b101 =
b101 7
b101 ?
b101 ;
#98000
b1001 <
b100100000011010010110111001100011011100100110010101101101011001010110111001110100 ^
1[
0]
b110 \
#99000
1&
b10000000000000000 W
1!
b0 "
b0 V
1D
b1111111111111111 =
b1111111111111111 7
b1111111111111111 ?
b100 :
#109000
b1010 <
b100000011010010110111001100011011100100110010101101101011001010110111001110100 ^
0[
1X
1]
b0 \
#110000
0$
0&
0!
1#
b100 "
b100 V
b100 W
0D
b11 9
b11 A
b101 =
b101 7
b101 ?
b110 ;
#120000
b1011 <
b100100000011001000110010101100011011100100110010101101101011001010110111001110100 ^
0X
0]
b100 \
#121000
1&
1%
1B
b11111111111111111 W
0!
0#
b1111111111111111 "
b1111111111111111 V
b0 =
b0 7
b0 ?
b101 :
#131000
b1100 <
b100000011001000110010101100011011100100110010101101101011001010110111001110100 ^
1Y
1X
b1111111111111111 \
#132000
0&
0%
0B
1C
b0 W
1!
b0 "
b0 V
b100 9
b100 A
b1111111100000000 >
b1111111100000000 8
b1111111100000000 @
b11111111 =
b11111111 7
b11111111 ?
b111 ;
#142000
b1101 <
b100000101001110010001000010000001111010011001010111001001101111 ^
0Y
0X
1]
b0 \
#143000
0C
0!
b1001000110000 "
b1001000110000 V
b101011001111000 >
b101011001111000 8
b101011001111000 @
b1001000110100 =
b1001000110100 7
b1001000110100 ?
b1000 ;
#153000
b1110 <
b1000100001000000111000001100001011101000111010001100101011100100110111001110011 ^
0]
b1001000110000 \
#154000
1%
1B
1C
0!
b1111111111111111 "
b1111111111111111 V
b101 9
b101 A
b1111111100000000 >
b1111111100000000 8
b1111111100000000 @
b11111111 =
b11111111 7
b11111111 ?
b1001 ;
#164000
b1111 <
b101010010001000000110000101101100011011000010000001101111011011100110010101110011 ^
1Y
b1111111111111111 \
#165000
0%
0B
0C
1#
0!
b100010001001100 "
b100010001001100 V
b110 9
b110 A
b101011001111000 >
b101011001111000 8
b101011001111000 @
b1001000110100 =
b1001000110100 7
b1001000110100 ?
b1010 ;
#175000
b10000 <
b101010010001000000111000001100001011101000111010001100101011100100110111001110011 ^
1[
0Y
b100010001001100 \
#176000
1%
1B
0!
0#
b1111111100000000 "
b1111111100000000 V
b111 9
b111 A
b0 >
b0 8
b0 @
b11111111 =
b11111111 7
b11111111 ?
b1011 ;
#186000
b10001 <
b10011100100111101010100 ^
0[
1Y
b1111111100000000 \
#187000
0!
b1111111111111111 "
b1111111111111111 V
b1110 9
b1110 A
b0 =
b0 7
b0 ?
b1100 ;
#197000
b10010 <
b1001110010000010100111001000100001000000111101001100101011100100110111101110011 ^
b1111111111111111 \
#198000
0%
0B
1C
1!
b0 "
b0 V
1D
b1111 9
b1111 A
b1111111111111111 >
b1111111111111111 8
b1111111111111111 @
b1111111111111111 =
b1111111111111111 7
b1111111111111111 ?
b1101 ;
#208000
b10011 <
b100111001001111010100100010000001101111011011100110010101110011 ^
0Y
1]
b0 \
#209000
0C
0!
1#
b10000 "
b10000 V
0D
b1000 9
b1000 A
b100 >
b100 8
b100 @
b1 =
b1 7
b1 ?
b1110 ;
#219000
b10100 <
b101001100010011000011101000100000001100010010000000111100001111000010000000110100 ^
0]
b10000 \
#220000
0!
1#
b100000000000 "
b100000000000 V
1D
b1001 9
b1001 A
b1000000000000000 =
b1000000000000000 7
b1000000000000000 ?
b110 :
#230000
b10101 <
b1111000001110000011000000110000001100000010000000111110001111100010000000110100 ^
b100000000000 \
#231000
1%
1B
0!
1#
b1111100000000000 "
b1111100000000000 V
b1010 9
b1010 A
b111 :
#241000
b10110 <
b101101001011001110110111000100000011001010111100001110100011001010110111001100100 ^
1Y
b1111100000000000 \
#242000
0!
0#
b1111111111111111 "
b1111111111111111 V
b10 >
b10 8
b10 @
b1111111111111111 =
b1111111111111111 7
b1111111111111111 ?
b1000 :
#252000
b10111 <
b100111010001000000110000101101100011011000010000001101111011011100110010101110011 ^
b1111111111111111 \
#253000
0%
0B
1#
0!
b1 "
b1 V
0D
b1011 9
b1011 A
b101 >
b101 8
b101 @
b101 =
b101 7
b101 ?
b1111 ;
#263000
b11000 <
b1000101011100010111010101100001011011000010000001110100011100100111010101100101 ^
0Y
b1 \
#264000
1!
0#
b0 "
b0 V
b11 >
b11 8
b11 @
b1001 :
#274000
b11001 <
b101110001011101010110000101101100001000000110011001100001011011000111001101100101 ^
1]
b0 \
#275000
0!
1#
b1 "
b1 V
b1100 9
b1100 A
b101 >
b101 8
b101 @
b11 =
b11 7
b11 ?
b10000 ;
#285000
b11010 <
b1010011010011000101010000111010001000000011001100100000001111000010000000110101 ^
0]
b1 \
#286000
0!
1#
b1 "
b1 V
1D
b1 >
b1 8
b1 @
b1111111111111110 =
b1111111111111110 7
b1111111111111110 ?
b1010 :
#296000
b11011 <
b111100001000000011000100100000011100110110100101100111011011100110010101100100 ^
#297000
1!
0#
b0 "
b0 V
b1101 9
b1101 A
b1011 :
#307000
b11100 <
b100000001101100011010100110101001100110011010000100000001111000010000000110001 ^
1]
b0 \
#308000
1%
1B
0!
1#
b1000000000000000 "
b1000000000000000 V
0D
b1000 9
b1000 A
b1111 >
b1111 8
b1111 @
b1 =
b1 7
b1 ?
b10001 ;
#318000
b11101 <
b1110011011010000110100101100110011101000010000001101100011001010110011001110100 ^
1Y
0]
b1000000000000000 \
#319000
0!
0#
b1111111111111111 "
b1111111111111111 V
1D
b110 9
b110 A
b101010101010101 >
b101010101010101 8
b101010101010101 @
b1010101010101010 =
b1010101010101010 7
b1010101010101010 ?
b1100 :
#329000
b11110 <
b101101110011001110010000001110000011000010111010001110100011001010111001001101110 ^
b1111111111111111 \
#330000
0%
0B
1!
b0 "
b0 V
0D
b100 9
b100 A
b0 >
b0 8
b0 @
b1 =
b1 7
b1 ?
b10010 ;
#340000
b11111 <
b1100011011011000110010101100001011100100111001100100000011000010110110001101100 ^
0Y
1]
b0 \
#341000
b10011 ;
