SINGLE_CYCLE_MIPS/mips_scp.v
`timescale 1ns/1ps

module mips_regfile #(parameter REGS = 32) (
    input  wire        clk,
    input  wire        rst,
    input  wire        write_en,
    input  wire [4:0]  read_a,
    input  wire [4:0]  read_b,
    input  wire [4:0]  write_a,
    input  wire [31:0] write_d,
    output wire [31:0] out_a,
    output wire [31:0] out_b
);

    reg [31:0] mem [0:REGS-1];
    integer i;

    assign out_a = (read_a == 5'b00000) ? 32'h00000000 : mem[read_a];
    assign out_b = (read_b == 5'b00000) ? 32'h00000000 : mem[read_b];

    always @(posedge clk or posedge rst) begin
        if (rst) begin
            for (i = 0; i < REGS; i = i + 1)
                mem[i] <= 32'h00000000;
        end else if (write_en && write_a != 5'b00000) begin
            mem[write_a] <= write_d;
        end
    end

endmodule

module mips_alu #(parameter WIDTH = 32) (
    input  wire [WIDTH-1:0] src_a,
    input  wire [WIDTH-1:0] src_b,
    input  wire [2:0]       func,
    output reg  [WIDTH-1:0] res,
    output wire             zero
);

    localparam [2:0] FN_AND = 3'b000;
    localparam [2:0] FN_OR  = 3'b001;
    localparam [2:0] FN_ADD = 3'b010;
    localparam [2:0] FN_SUB = 3'b110;
    localparam [2:0] FN_SLT = 3'b111;
    localparam [2:0] FN_NOR = 3'b100;

    always @(*) begin
        case (func)
            FN_AND: res = src_a & src_b;
            FN_OR:  res = src_a | src_b;
            FN_ADD: res = src_a + src_b;
            FN_SUB: res = src_a - src_b;
            FN_SLT: res = ($signed(src_a) < $signed(src_b)) ? 32'h00000001 : 32'h00000000;
            FN_NOR: res = ~(src_a | src_b);
            default: res = 32'h00000000;
        endcase
    end

    assign zero = (res == 32'h00000000);

endmodule

module mips_alu_dec (
    input  wire [5:0] funct,
    input  wire [1:0] alu_op,
    output reg  [2:0] alu_ctrl
);

    always @(*) begin
        case (alu_op)
            2'b00: alu_ctrl = 3'b010;
            2'b01: alu_ctrl = 3'b110;
            2'b10: begin
                case (funct)
                    6'b100000: alu_ctrl = 3'b010;
                    6'b100010: alu_ctrl = 3'b110;
                    6'b100100: alu_ctrl = 3'b000;
                    6'b100101: alu_ctrl = 3'b001;
                    6'b101010: alu_ctrl = 3'b111;
                    default:   alu_ctrl = 3'b000;
                endcase
            end
            default: alu_ctrl = 3'b000;
        endcase
    end

endmodule

module mips_ctrl (
    input  wire [5:0] op,
    output reg        reg_w,
    output reg        reg_d,
    output reg        alu_s,
    output reg        branch,
    output reg        mem_w,
    output reg        mem_r,
    output reg        jump,
    output reg [1:0] alu_op
);

    localparam [5:0] OP_RTYPE = 6'b000000;
    localparam [5:0] OP_LW    = 6'b100011;
    localparam [5:0] OP_SW    = 6'b101011;
    localparam [5:0] OP_BEQ   = 6'b000100;
    localparam [5:0] OP_ADDI  = 6'b001000;
    localparam [5:0] OP_ANDI  = 6'b001100;
    localparam [5:0] OP_ORI   = 6'b001101;
    localparam [5:0] OP_J     = 6'b000010;

    always @(*) begin
        reg_w = 1'b0;
        reg_d = 1'b0;
        alu_s = 1'b0;
        branch = 1'b0;
        mem_w = 1'b0;
        mem_r = 1'b0;
        jump = 1'b0;
        alu_op = 2'b00;

        case (op)
            OP_RTYPE: begin
                reg_w = 1'b1;
                reg_d = 1'b1;
                alu_op = 2'b10;
            end
            OP_LW: begin
                reg_w = 1'b1;
                alu_s = 1'b1;
                mem_r = 1'b1;
                alu_op = 2'b00;
            end
            OP_SW: begin
                alu_s = 1'b1;
                mem_w = 1'b1;
                alu_op = 2'b00;
            end
            OP_BEQ: begin
                branch = 1'b1;
                alu_op = 2'b01;
            end
            OP_ADDI: begin
                reg_w = 1'b1;
                alu_s = 1'b1;
                alu_op = 2'b00;
            end
            OP_ANDI: begin
                reg_w = 1'b1;
                alu_s = 1'b1;
                alu_op = 2'b10;
            end
            OP_ORI: begin
                reg_w = 1'b1;
                alu_s = 1'b1;
                alu_op = 2'b10;
            end
            OP_J: begin
                jump = 1'b1;
            end
            default: begin
            end
        endcase
    end

endmodule

module mips_scp (
    input  wire        clk,
    input  wire        rst,
    output wire [31:0] pc,
    input  wire [31:0] instr,
    output wire [31:0] mem_addr,
    output wire [31:0] mem_write,
    output wire        mem_we,
    input  wire [31:0] mem_read
);

    wire [5:0]  op;
    wire [4:0]  rs, rt, rd;
    wire [15:0] imm;
    wire [5:0]  func;
    wire [25:0] jaddr;

    assign op = instr[31:26];
    assign rs = instr[25:21];
    assign rt = instr[20:16];
    assign rd = instr[15:11];
    assign func = instr[5:0];
    assign imm = instr[15:0];
    assign jaddr = instr[25:0];

    wire reg_w, reg_d, alu_s, branch, mem_w, mem_r, jump;
    wire [1:0] alu_op;

    mips_ctrl CTRL (
        .op(op),
        .reg_w(reg_w),
        .reg_d(reg_d),
        .alu_s(alu_s),
        .branch(branch),
        .mem_w(mem_w),
        .mem_r(mem_r),
        .jump(jump),
        .alu_op(alu_op)
    );

    wire [2:0] alu_ctrl;
    mips_alu_dec ALU_DEC (
        .funct(func),
        .alu_op(alu_op),
        .alu_ctrl(alu_ctrl)
    );

    wire [4:0] wr_reg;
    wire [31:0] wr_data;
    wire [31:0] rd1, rd2;

    assign wr_reg = reg_d ? rd : rt;

    mips_regfile #(.REGS(32)) RF (
        .clk(clk),
        .rst(rst),
        .write_en(reg_w),
        .read_a(rs),
        .read_b(rt),
        .write_a(wr_reg),
        .write_d(wr_data),
        .out_a(rd1),
        .out_b(rd2)
    );

    wire [31:0] imm_ext;
    assign imm_ext = {{16{imm[15]}}, imm};

    wire [31:0] alu_b;
    wire [31:0] alu_res;
    wire        alu_zero;

    assign alu_b = alu_s ? imm_ext : rd2;

    mips_alu #(.WIDTH(32)) ALU (
        .src_a(rd1),
        .src_b(alu_b),
        .func(alu_ctrl),
        .res(alu_res),
        .zero(alu_zero)
    );

    assign mem_addr = alu_res;
    assign mem_write = rd2;
    assign mem_we = mem_w;

    assign wr_data = mem_r ? mem_read : alu_res;

    reg [31:0] pc_r;
    wire [31:0] pc_inc;
    wire [31:0] pc_tgt;
    wire [31:0] pc_jump;
    wire        pc_src;

    assign pc = pc_r;
    assign pc_inc = pc_r + 32'h00000004;
    assign pc_tgt = pc_inc + (imm_ext << 2);
    assign pc_jump = {pc_inc[31:28], jaddr, 2'b00};
    assign pc_src = branch & alu_zero;

    wire [31:0] pc_next_val;
    assign pc_next_val = jump ? pc_jump : (pc_src ? pc_tgt : pc_inc);

    always @(posedge clk or posedge rst) begin
        if (rst)
            pc_r <= 32'h00000000;
        else
            pc_r <= pc_next_val;
    end

endmodule

SINGLE_CYCLE_MIPS/tb_mips_scp.v
`timescale 1ns/1ps

module tb_mips_scp;

    reg         clk;
    reg         rst;
    wire [31:0] pc;
    wire [31:0] mem_addr;
    wire [31:0] mem_write;
    wire        mem_we;

    reg [31:0] iram [0:255];
    reg [31:0] dram [0:255];
    wire [31:0] instr;
    reg [31:0] mem_read;

    integer cycle;
    integer max_cyc;
    integer i;

    function [31:0] make_rtype;
        input [5:0] fn;
        input [4:0] r_s, r_t, r_d;
        begin
            make_rtype = {6'b000000, r_s, r_t, r_d, 5'b00000, fn};
        end
    endfunction

    function [31:0] make_itype;
        input [5:0] op;
        input [4:0] r_s, r_t;
        input [15:0] i_val;
        begin
            make_itype = {op, r_s, r_t, i_val};
        end
    endfunction

    function [31:0] make_jtype;
        input [5:0] op;
        input [25:0] j_addr;
        begin
            make_jtype = {op, j_addr};
        end
    endfunction

    mips_scp DUT (
        .clk(clk),
        .rst(rst),
        .pc(pc),
        .instr(instr),
        .mem_addr(mem_addr),
        .mem_write(mem_write),
        .mem_we(mem_we),
        .mem_read(mem_read)
    );

    initial begin
        clk = 1'b0;
        forever #5 clk = ~clk;
    end

    assign instr = iram[pc[9:2]];

    always @(posedge clk) begin
        if (mem_we) begin
            dram[mem_addr[9:2]] <= mem_write;
            $display("[%0t] WRITE: Addr=0x%h, Data=0x%h", $time, mem_addr, mem_write);
        end
    end

    always @(*) begin
        mem_read = dram[mem_addr[9:2]];
    end

    initial begin
        $display("====================================================");
        $display("      Single-Cycle MIPS Processor Test");
        $display("====================================================\n");

        // Initialize all instruction memory to NOP to avoid x's
        for (i = 0; i < 256; i = i + 1)
            iram[i] = 32'h00000000;

        // Initialize all data memory to zero to avoid x's
        for (i = 0; i < 256; i = i + 1)
            dram[i] = 32'h00000000;

        iram[0]  = make_itype(6'b001000, 5'd0, 5'd1, 16'd8);
        iram[1]  = make_itype(6'b001000, 5'd0, 5'd2, 16'd12);
        iram[2]  = make_itype(6'b001000, 5'd0, 5'd3, 16'd4);
        iram[3]  = make_itype(6'b001000, 5'd0, 5'd4, 16'hFFFD);

        iram[4]  = make_rtype(6'b100000, 5'd1, 5'd2, 5'd5);
        iram[5]  = make_rtype(6'b100010, 5'd2, 5'd3, 5'd6);

        iram[6]  = make_rtype(6'b100100, 5'd1, 5'd2, 5'd7);
        iram[7]  = make_rtype(6'b100101, 5'd1, 5'd2, 5'd8);

        iram[8]  = make_rtype(6'b101010, 5'd1, 5'd2, 5'd9);
        iram[9]  = make_rtype(6'b101010, 5'd2, 5'd1, 5'd10);

        iram[10] = make_itype(6'b101011, 5'd0, 5'd5, 16'd0);
        iram[11] = make_itype(6'b101011, 5'd0, 5'd6, 16'd4);
        iram[12] = make_itype(6'b101011, 5'd0, 5'd9, 16'd8);

        iram[13] = make_itype(6'b100011, 5'd0, 5'd11, 16'd0);
        iram[14] = make_itype(6'b100011, 5'd0, 5'd12, 16'd4);

        iram[15] = make_itype(6'b000100, 5'd1, 5'd1, 16'd1);
        iram[16] = make_itype(6'b001000, 5'd0, 5'd13, 16'd999);
        iram[17] = make_itype(6'b001000, 5'd0, 5'd13, 16'd100);

        iram[18] = make_itype(6'b000100, 5'd1, 5'd2, 16'd1);
        iram[19] = make_itype(6'b001000, 5'd0, 5'd14, 16'd200);

        iram[20] = make_jtype(6'b000010, 26'd21);

        rst = 1'b1;
        cycle = 0;
        max_cyc = 30;
        #20;
        rst = 1'b0;

        $display("Starting execution...\n");
        $display("Cyc  PC       Instr       OP    Halted");
        $display("---- -------- ----------- ---- ------");

        while (cycle < max_cyc) begin
            @(posedge clk);
            $display("%3d  0x%06h  0x%08h  %b", 
                     cycle, pc, instr, instr[31:26]);
            cycle = cycle + 1;
        end

        $display("\n====================================================");
        $display("Register Values:");
        $display("  $1  = 0x%08h (exp: 0x00000008 = 8)", DUT.RF.mem[1]);
        $display("  $2  = 0x%08h (exp: 0x0000000C = 12)", DUT.RF.mem[2]);
        $display("  $3  = 0x%08h (exp: 0x00000004 = 4)", DUT.RF.mem[3]);
        $display("  $4  = 0x%08h (exp: 0xFFFFFFFD = -3)", DUT.RF.mem[4]);
        $display("  $5  = 0x%08h (exp: 0x00000014 = 20)", DUT.RF.mem[5]);
        $display("  $6  = 0x%08h (exp: 0x00000008 = 8)", DUT.RF.mem[6]);
        $display("  $7  = 0x%08h", DUT.RF.mem[7]);
        $display("  $8  = 0x%08h", DUT.RF.mem[8]);
        $display("  $9  = 0x%08h (exp: 0x00000001)", DUT.RF.mem[9]);
        $display("  $10 = 0x%08h (exp: 0x00000000)", DUT.RF.mem[10]);
        $display("  $11 = 0x%08h (exp: 0x00000014)", DUT.RF.mem[11]);
        $display("  $12 = 0x%08h (exp: 0x00000008)", DUT.RF.mem[12]);
        $display("  $13 = 0x%08h (exp: 0x00000064 = 100)", DUT.RF.mem[13]);
        $display("  $14 = 0x%08h (exp: 0x000000C8 = 200)", DUT.RF.mem[14]);

        $display("\nMemory Values:");
        $display("  Mem[0] = 0x%08h (exp: 0x00000014 = 20)", dram[0]);
        $display("  Mem[1] = 0x%08h (exp: 0x00000008 = 8)", dram[1]);
        $display("  Mem[2] = 0x%08h (exp: 0x00000001)", dram[2]);

        if (DUT.RF.mem[5] == 32'h00000014 && 
            DUT.RF.mem[6] == 32'h00000008 && 
            DUT.RF.mem[9] == 32'h00000001 &&
            dram[0] == 32'h00000014) begin
            $display("\nResult: PASSED");
        end else begin
            $display("\nResult: FAILED");
        end

        $display("Total Cycles: %0d", cycle);
        $display("====================================================\n");

        $finish;
    end

    initial begin
        $dumpfile("mips_scp.vcd");
        $dumpvars(0, tb_mips_scp);
    end

endmodule

SINGLE_CYCLE_MIPS/mips_scp.vcd
$date
	Fri Jan 30 23:45:36 2026
$end
$version
	Icarus Verilog
$end
$timescale
	1ps
$end
$scope module tb_mips_scp $end
$var wire 32 ! instr [31:0] $end
$var wire 32 " pc [31:0] $end
$var wire 32 # mem_write [31:0] $end
$var wire 1 $ mem_we $end
$var wire 32 % mem_addr [31:0] $end
$var reg 1 & clk $end
$var reg 32 ' mem_read [31:0] $end
$var reg 1 ( rst $end
$var integer 32 ) cycle [31:0] $end
$var integer 32 * i [31:0] $end
$var integer 32 + max_cyc [31:0] $end
$scope function make_itype $end
$var reg 16 , i_val [15:0] $end
$var reg 6 - op [5:0] $end
$var reg 5 . r_s [4:0] $end
$var reg 5 / r_t [4:0] $end
$upscope $end
$scope function make_jtype $end
$var reg 26 0 j_addr [25:0] $end
$var reg 6 1 op [5:0] $end
$upscope $end
$scope function make_rtype $end
$var reg 6 2 fn [5:0] $end
$var reg 5 3 r_d [4:0] $end
$var reg 5 4 r_s [4:0] $end
$var reg 5 5 r_t [4:0] $end
$upscope $end
$scope module DUT $end
$var wire 1 & clk $end
$var wire 32 6 instr [31:0] $end
$var wire 32 7 mem_addr [31:0] $end
$var wire 32 8 mem_read [31:0] $end
$var wire 1 $ mem_we $end
$var wire 32 9 mem_write [31:0] $end
$var wire 32 : pc [31:0] $end
$var wire 1 ; pc_src $end
$var wire 1 ( rst $end
$var wire 5 < wr_reg [4:0] $end
$var wire 32 = wr_data [31:0] $end
$var wire 5 > rt [4:0] $end
$var wire 5 ? rs [4:0] $end
$var wire 1 @ reg_w $end
$var wire 1 A reg_d $end
$var wire 32 B rd2 [31:0] $end
$var wire 32 C rd1 [31:0] $end
$var wire 5 D rd [4:0] $end
$var wire 32 E pc_tgt [31:0] $end
$var wire 32 F pc_next_val [31:0] $end
$var wire 32 G pc_jump [31:0] $end
$var wire 32 H pc_inc [31:0] $end
$var wire 6 I op [5:0] $end
$var wire 1 J mem_w $end
$var wire 1 K mem_r $end
$var wire 1 L jump $end
$var wire 26 M jaddr [25:0] $end
$var wire 32 N imm_ext [31:0] $end
$var wire 16 O imm [15:0] $end
$var wire 6 P func [5:0] $end
$var wire 1 Q branch $end
$var wire 1 R alu_zero $end
$var wire 1 S alu_s $end
$var wire 32 T alu_res [31:0] $end
$var wire 2 U alu_op [1:0] $end
$var wire 3 V alu_ctrl [2:0] $end
$var wire 32 W alu_b [31:0] $end
$var reg 32 X pc_r [31:0] $end
$scope module ALU $end
$var wire 32 Y src_b [31:0] $end
$var wire 1 R zero $end
$var wire 32 Z src_a [31:0] $end
$var wire 3 [ func [2:0] $end
$var parameter 3 \ FN_ADD $end
$var parameter 3 ] FN_AND $end
$var parameter 3 ^ FN_NOR $end
$var parameter 3 _ FN_OR $end
$var parameter 3 ` FN_SLT $end
$var parameter 3 a FN_SUB $end
$var parameter 32 b WIDTH $end
$var reg 32 c res [31:0] $end
$upscope $end
$scope module ALU_DEC $end
$var wire 6 d funct [5:0] $end
$var wire 2 e alu_op [1:0] $end
$var reg 3 f alu_ctrl [2:0] $end
$upscope $end
$scope module CTRL $end
$var wire 6 g op [5:0] $end
$var parameter 6 h OP_ADDI $end
$var parameter 6 i OP_ANDI $end
$var parameter 6 j OP_BEQ $end
$var parameter 6 k OP_J $end
$var parameter 6 l OP_LW $end
$var parameter 6 m OP_ORI $end
$var parameter 6 n OP_RTYPE $end
$var parameter 6 o OP_SW $end
$var reg 2 p alu_op [1:0] $end
$var reg 1 S alu_s $end
$var reg 1 Q branch $end
$var reg 1 L jump $end
$var reg 1 K mem_r $end
$var reg 1 J mem_w $end
$var reg 1 A reg_d $end
$var reg 1 @ reg_w $end
$upscope $end
$scope module RF $end
$var wire 1 & clk $end
$var wire 5 q read_a [4:0] $end
$var wire 5 r read_b [4:0] $end
$var wire 1 ( rst $end
$var wire 5 s write_a [4:0] $end
$var wire 32 t write_d [31:0] $end
$var wire 1 @ write_en $end
$var wire 32 u out_b [31:0] $end
$var wire 32 v out_a [31:0] $end
$var parameter 32 w REGS $end
$var integer 32 x i [31:0] $end
$upscope $end
$upscope $end
$upscope $end
$enddefinitions $end
$comment Show the parameter values. $end
$dumpall
b100000 w
b101011 o
b0 n
b1101 m
b100011 l
b10 k
b100 j
b1100 i
b1000 h
b100000 b
b110 a
b111 `
b1 _
b100 ^
b0 ]
b10 \
$end
#0
$dumpvars
b100000 x
b0 v
b0 u
b1000 t
b1 s
b1 r
b0 q
b0 p
b1000 g
b10 f
b0 e
b1000 d
b1000 c
b10 [
b0 Z
b1000 Y
b0 X
b1000 W
b10 V
b0 U
b1000 T
1S
0R
0Q
b1000 P
b1000 O
b1000 N
b10000000000001000 M
0L
0K
0J
b1000 I
b100 H
b1000000000000100000 G
b100 F
b100100 E
b0 D
b0 C
b0 B
0A
1@
b0 ?
b1 >
b1000 =
b1 <
0;
b0 :
b0 9
b0 8
b1000 7
b100000000000010000000000001000 6
b1 5
b10 4
b1010 3
b101010 2
b10 1
b10101 0
b1110 /
b0 .
b1000 -
b11001000 ,
b11110 +
b100000000 *
b0 )
1(
b0 '
0&
b1000 %
0$
b0 #
b0 "
b100000000000010000000000001000 !
$end
#5000
b100000 x
1&
#10000
0&
#15000
b100000 x
1&
#20000
0&
0(
#25000
b1100 =
b1100 t
b1100 %
b1100 7
b1100 T
b1100 c
b10 <
b10 s
b1100 W
b1100 Y
b1000 F
b10 >
b10 r
b1100 P
b1100 d
b1100 N
b1100 O
b10000000000000110000 G
b100000000000001100 M
b100000000000100000000000001100 !
b100000000000100000000000001100 6
b0 #
b0 9
b0 B
b0 u
b111000 E
b1000 H
b100 "
b100 :
b100 X
b1 )
1&
#30000
0&
#35000
b100 =
b100 t
b100 %
b100 7
b100 T
b100 c
b11 <
b11 s
b100 W
b100 Y
b1100 F
b11 >
b11 r
b100 P
b100 d
b100 N
b100 O
b11000000000000010000 G
b110000000000000100 M
b0 #
b0 9
b0 B
b0 u
b100000000000110000000000000100 !
b100000000000110000000000000100 6
b11100 E
b1100 H
b1000 "
b1000 :
b1000 X
b10 )
1&
#40000
0&
#45000
b11111111111111111111111111111101 =
b11111111111111111111111111111101 t
b11111111111111111111111111111101 %
b11111111111111111111111111111101 7
b11111111111111111111111111111101 T
b11111111111111111111111111111101 c
b100 <
b100 s
b11111111111111111111111111111101 W
b11111111111111111111111111111101 Y
b10000 F
b100 >
b100 r
b11111 D
b111101 P
b111101 d
b11111111111111111111111111111101 N
b1111111111111101 O
b100111111111111110100 G
b1001111111111111101 M
b100000000001001111111111111101 !
b100000000001001111111111111101 6
b0 #
b0 9
b0 B
b0 u
b100 E
b10000 H
b1100 "
b1100 :
b1100 X
b11 )
1&
#50000
0&
#55000
b10100 =
b10100 t
b10100 %
b10100 7
b10100 T
b10100 c
b10 U
b10 e
b10 p
1A
0S
1@
b1000 C
b1000 Z
b1000 v
b101 <
b101 s
b1100 W
b1100 Y
b10100 F
b0 I
b0 g
b1 ?
b1 q
b10 >
b10 r
b101 D
b100000 P
b100000 d
b10100000100000 N
b10100000100000 O
b100010001010000010000000 G
b1000100010100000100000 M
b1100 #
b1100 9
b1100 B
b1100 u
b1000100010100000100000 !
b1000100010100000100000 6
b1010000010010100 E
b10100 H
b10000 "
b10000 :
b10000 X
b100 )
1&
#60000
0&
#65000
b1000 =
b1000 t
b100 W
b100 Y
0R
b1000 %
b1000 7
b1000 T
b1000 c
b1100 C
b1100 Z
b1100 v
b100 #
b100 9
b100 B
b100 u
b110 <
b110 s
b110 V
b110 [
b110 f
b11000 F
b10 ?
b10 q
b11 >
b11 r
b110 D
b100010 P
b100010 d
b11000000100010 N
b11000000100010 O
b1000011001100000010001000 G
b10000110011000000100010 M
b10000110011000000100010 !
b10000110011000000100010 6
b1100000010100000 E
b11000 H
b10100 "
b10100 :
b10100 X
b101 )
1&
#70000
0&
#75000
b1000 =
b1000 t
b1100 W
b1100 Y
0R
b1000 %
b1000 7
b1000 T
b1000 c
b1000 C
b1000 Z
b1000 v
b1100 #
b1100 9
b1100 B
b1100 u
b111 <
b111 s
b0 V
b0 [
b0 f
b11100 F
b1 ?
b1 q
b10 >
b10 r
b111 D
b100100 P
b100100 d
b11100000100100 N
b11100000100100 O
b100010001110000010010000 G
b1000100011100000100100 M
b1000100011100000100100 !
b1000100011100000100100 6
b1110000010101100 E
b11100 H
b11000 "
b11000 :
b11000 X
b110 )
1&
#80000
0&
#85000
b1100 =
b1100 t
b1100 %
b1100 7
b1100 T
b1100 c
b1000 <
b1000 s
b1 V
b1 [
b1 f
b100000 F
b1000 D
b100101 P
b100101 d
b100000000100101 N
b100000000100101 O
b100010010000000010010100 G
b1000100100000000100101 M
b1000100100000000100101 !
b1000100100000000100101 6
b10000000010110100 E
b100000 H
b11100 "
b11100 :
b11100 X
b111 )
1&
#90000
0&
#95000
b1 =
b1 t
b1 %
b1 7
b1 T
b1 c
b1001 <
b1001 s
b111 V
b111 [
b111 f
b100100 F
b1001 D
b101010 P
b101010 d
b100100000101010 N
b100100000101010 O
b100010010010000010101000 G
b1000100100100000101010 M
b1000100100100000101010 !
b1000100100100000101010 6
b10010000011001100 E
b100100 H
b100000 "
b100000 :
b100000 X
b1000 )
1&
#100000
0&
#105000
b0 =
b0 t
1R
b0 %
b0 7
b0 T
b0 c
b1000 W
b1000 Y
b1100 C
b1100 Z
b1100 v
b1000 #
b1000 9
b1000 B
b1000 u
b1010 <
b1010 s
b101000 F
b10 ?
b10 q
b1 >
b1 r
b1010 D
b101000000101010 N
b101000000101010 O
b1000001010100000010101000 G
b10000010101000000101010 M
b10000010101000000101010 !
b10000010101000000101010 6
b10100000011010000 E
b101000 H
b100100 "
b100100 :
b100100 X
b1001 )
1&
#110000
0&
#115000
b0 W
b0 Y
1$
1J
1S
b0 U
b0 e
b0 p
0A
0@
b0 C
b0 Z
b0 v
b10100 #
b10100 9
b10100 B
b10100 u
b101 <
b101 s
b10 V
b10 [
b10 f
b101100 F
b101011 I
b101011 g
b0 ?
b0 q
b101 >
b101 r
b0 D
b0 P
b0 d
b0 N
b0 O
b101000000000000000000 G
b1010000000000000000 M
b10101100000001010000000000000000 !
b10101100000001010000000000000000 6
b101100 E
b101100 H
b101000 "
b101000 :
b101000 X
b1010 )
1&
#120000
0&
#125000
b100 =
b100 t
0R
b100 %
b100 7
b100 T
b100 c
b110 <
b110 s
b1000 #
b1000 9
b1000 B
b1000 u
b100 W
b100 Y
b110000 F
b110 >
b110 r
b100 P
b100 d
b100 N
b100 O
b110000000000000010000 G
b1100000000000000100 M
b10101100000001100000000000000100 !
b10101100000001100000000000000100 6
b0 '
b0 8
b1000000 E
b110000 H
b101100 "
b101100 :
b101100 X
b1011 )
1&
#130000
0&
#135000
b1000 =
b1000 t
b1000 %
b1000 7
b1000 T
b1000 c
b1001 <
b1001 s
b1 #
b1 9
b1 B
b1 u
b1000 W
b1000 Y
b110100 F
b1001 >
b1001 r
b1000 P
b1000 d
b1000 N
b1000 O
b1001000000000000100000 G
b10010000000000001000 M
b10101100000010010000000000001000 !
b10101100000010010000000000001000 6
b0 '
b0 8
b1010100 E
b110100 H
b110000 "
b110000 :
b110000 X
b1100 )
1&
#140000
0&
#145000
b10100 =
b10100 t
1R
b0 %
b0 7
b0 T
b0 c
1K
1@
0$
0J
1S
b1011 <
b1011 s
b0 #
b0 9
b0 B
b0 u
b0 W
b0 Y
b111000 F
b100011 I
b100011 g
b1011 >
b1011 r
b0 P
b0 d
b0 N
b0 O
b1011000000000000000000 G
b10110000000000000000 M
b10001100000010110000000000000000 !
b10001100000010110000000000000000 6
b10100 '
b10100 8
b111000 E
b111000 H
b110100 "
b110100 :
b110100 X
b1101 )
1&
#150000
0&
#155000
b1000 =
b1000 t
b1000 '
b1000 8
0R
b100 %
b100 7
b100 T
b100 c
b1100 <
b1100 s
b100 W
b100 Y
b111100 F
b1100 >
b1100 r
b100 P
b100 d
b100 N
b100 O
b1100000000000000010000 G
b11000000000000000100 M
b0 #
b0 9
b0 B
b0 u
b10001100000011000000000000000100 !
b10001100000011000000000000000100 6
b1001100 E
b111100 H
b111000 "
b111000 :
b111000 X
b1110 )
1&
#160000
0&
#165000
1;
1R
b10100 '
b10100 8
b110 V
b110 [
b110 f
b0 =
b0 t
b0 %
b0 7
b0 T
b0 c
b1 U
b1 e
b1 p
1Q
0K
0S
0@
b1000 C
b1000 Z
b1000 v
b1 <
b1 s
b1000 W
b1000 Y
b1000100 F
b100 I
b100 g
b1 ?
b1 q
b1 >
b1 r
b1 P
b1 d
b1 N
b1 O
b100001000000000000000100 G
b1000010000000000000001 M
b10000001000010000000000000001 !
b10000001000010000000000000001 6
b1000 #
b1000 9
b1000 B
b1000 u
b1000100 E
b1000000 H
b111100 "
b111100 :
b111100 X
b1111 )
1&
#170000
0&
#175000
b1100100 =
b1100100 t
b0 '
b0 8
b10 V
b10 [
b10 f
0;
0R
b1100100 %
b1100100 7
b1100100 T
b1100100 c
b1100100 W
b1100100 Y
1S
1@
b0 U
b0 e
b0 p
0Q
b0 C
b0 Z
b0 v
b1101 <
b1101 s
b0 #
b0 9
b0 B
b0 u
b1001000 F
b1000 I
b1000 g
b0 ?
b0 q
b1101 >
b1101 r
b100100 P
b100100 d
b1100100 N
b1100100 O
b1101000000000110010000 G
b11010000000001100100 M
b100000000011010000000001100100 !
b100000000011010000000001100100 6
b111011000 E
b1001000 H
b1000100 "
b1000100 :
b1000100 X
b10000 )
1&
#180000
0&
#185000
b11111111111111111111111111111100 =
b11111111111111111111111111111100 t
b0 '
b0 8
b110 V
b110 [
b110 f
b11111111111111111111111111111100 %
b11111111111111111111111111111100 7
b11111111111111111111111111111100 T
b11111111111111111111111111111100 c
b1 U
b1 e
b1 p
1Q
0S
0@
b1000 C
b1000 Z
b1000 v
b10 <
b10 s
b1100 W
b1100 Y
b1001100 F
b100 I
b100 g
b1 ?
b1 q
b10 >
b10 r
b1 P
b1 d
b1 N
b1 O
b100010000000000000000100 G
b1000100000000000000001 M
b10000001000100000000000000001 !
b10000001000100000000000000001 6
b1100 #
b1100 9
b1100 B
b1100 u
b1010000 E
b1001100 H
b1001000 "
b1001000 :
b1001000 X
b10001 )
1&
#190000
0&
#195000
b11001000 =
b11001000 t
b10 V
b10 [
b10 f
b11001000 %
b11001000 7
b11001000 T
b11001000 c
b11001000 W
b11001000 Y
1S
1@
b0 U
b0 e
b0 p
0Q
b0 C
b0 Z
b0 v
b1110 <
b1110 s
b0 #
b0 9
b0 B
b0 u
b1010000 F
b1000 I
b1000 g
b0 ?
b0 q
b1110 >
b1110 r
b1000 P
b1000 d
b11001000 N
b11001000 O
b1110000000001100100000 G
b11100000000011001000 M
b100000000011100000000011001000 !
b100000000011100000000011001000 6
b1101110000 E
b1010000 H
b1001100 "
b1001100 :
b1001100 X
b10010 )
1&
#200000
0&
#205000
b10100 '
b10100 8
1R
b0 =
b0 t
b0 %
b0 7
b0 T
b0 c
1L
0S
0@
b0 <
b0 s
b0 W
b0 Y
b1010100 F
b10 I
b10 g
b0 >
b0 r
b10101 P
b10101 d
b10101 N
b10101 O
b1010100 G
b10101 M
b1000000000000000000000010101 !
b1000000000000000000000010101 6
b0 #
b0 9
b0 B
b0 u
b10101000 E
b1010100 H
b1010000 "
b1010000 :
b1010000 X
b10011 )
1&
#210000
0&
#215000
b0 V
b0 [
b0 f
b10 U
b10 e
b10 p
1A
1@
0L
b1011000 F
b0 I
b0 g
b0 P
b0 d
b0 N
b0 O
b0 G
b0 M
b0 !
b0 6
b1011000 E
b1011000 H
b1010100 "
b1010100 :
b1010100 X
b10100 )
1&
#220000
0&
#225000
b1011100 F
b1011100 E
b1011100 H
b1011000 "
b1011000 :
b1011000 X
b10101 )
1&
#230000
0&
#235000
b1100000 F
b1100000 E
b1100000 H
b1011100 "
b1011100 :
b1011100 X
b10110 )
1&
#240000
0&
#245000
b1100100 F
b1100100 E
b1100100 H
b1100000 "
b1100000 :
b1100000 X
b10111 )
1&
#250000
0&
#255000
b1101000 F
b1101000 E
b1101000 H
b1100100 "
b1100100 :
b1100100 X
b11000 )
1&
#260000
0&
#265000
b1101100 F
b1101100 E
b1101100 H
b1101000 "
b1101000 :
b1101000 X
b11001 )
1&
#270000
0&
#275000
b1110000 F
b1110000 E
b1110000 H
b1101100 "
b1101100 :
b1101100 X
b11010 )
1&
#280000
0&
#285000
b1110100 F
b1110100 E
b1110100 H
b1110000 "
b1110000 :
b1110000 X
b11011 )
1&
#290000
0&
#295000
b1111000 F
b1111000 E
b1111000 H
b1110100 "
b1110100 :
b1110100 X
b11100 )
1&
#300000
0&
#305000
b1111100 F
b1111100 E
b1111100 H
b1111000 "
b1111000 :
b1111000 X
b11101 )
1&
#310000
0&
#315000
b10000000 F
b10000000 E
b10000000 H
b1111100 "
b1111100 :
b1111100 X
b11110 )
1&
